airbyte_serverless/__init__.py
airbyte_serverless/airbyte_utils.py
airbyte_serverless/cli.py
airbyte_serverless/connections.py
airbyte_serverless/destinations.py
airbyte_serverless/runners.py
airbyte_serverless/sources.py
airbyte_serverless/version.py
airbyte_serverless-0.37.dist-info/licenses/LICENSE
airbyte_serverless-0.37.dist-info/METADATA
airbyte_serverless-0.37.dist-info/WHEEL
airbyte_serverless-0.37.dist-info/entry_points.txt
airbyte_serverless-0.37.dist-info/top_level.txt
airbyte_serverless-0.37.dist-info/RECORD
