Metadata-Version: 2.4
Name: airbyte_serverless
Version: 0.37
Summary: Airbyte made easy (no UI, no database, no cluster)
Download-URL: https://github.com/unytics/airbyte_serverless/archive/refs/tags/v0.37.tar.gz
Author: Unytics
Author-email: paul.marcombes@unytics.io
Classifier: Programming Language :: Python :: 3
Classifier: License :: OSI Approved :: MIT License
Classifier: Operating System :: OS Independent
Requires-Python: >=3.6
License-File: LICENSE
Requires-Dist: google-cloud-bigquery
Requires-Dist: google-cloud-run
Requires-Dist: google-cloud-secret-manager
Requires-Dist: pyyaml
Requires-Dist: jinja2
Requires-Dist: click
Requires-Dist: click-help-colors
Requires-Dist: pipx
Dynamic: author
Dynamic: author-email
Dynamic: classifier
Dynamic: description
Dynamic: description-content-type
Dynamic: download-url
Dynamic: license-file
Dynamic: requires-dist
Dynamic: requires-python
Dynamic: summary
